responsibleai/__init__.py
responsibleai/__version__.py
responsibleai/_data_validations.py
responsibleai/_interfaces.py
responsibleai/exceptions.py
responsibleai/feature_metadata.py
responsibleai/serialization_utilities.py
responsibleai/utils.py
responsibleai/_config/__init__.py
responsibleai/_config/base_config.py
responsibleai/_internal/__init__.py
responsibleai/_internal/_forecasting_wrappers.py
responsibleai/_internal/_served_model_wrapper.py
responsibleai/_internal/constants.py
responsibleai/_tools/__init__.py
responsibleai/_tools/causal/__init__.py
responsibleai/_tools/causal/causal_config.py
responsibleai/_tools/causal/causal_constants.py
responsibleai/_tools/causal/causal_result.py
responsibleai/_tools/causal/dashboard_schemas/__init__.py
responsibleai/_tools/causal/dashboard_schemas/schema_0.1.0.json
responsibleai/_tools/counterfactual/__init__.py
responsibleai/_tools/counterfactual/dashboard_schemas/__init__.py
responsibleai/_tools/counterfactual/dashboard_schemas/counterfactual_examples_output_v1.0.json
responsibleai/_tools/counterfactual/dashboard_schemas/counterfactual_examples_output_v2.0.json
responsibleai/_tools/error_analysis/__init__.py
responsibleai/_tools/error_analysis/dashboard_schemas/__init__.py
responsibleai/_tools/error_analysis/dashboard_schemas/error_analysis_output_v0.0.json
responsibleai/_tools/shared/__init__.py
responsibleai/_tools/shared/attribute_serialization.py
responsibleai/_tools/shared/base_result.py
responsibleai/_tools/shared/state_directory_management.py
responsibleai/_tools/shared/versions.py
responsibleai/databalanceanalysis/__init__.py
responsibleai/databalanceanalysis/aggregate_balance_measures.py
responsibleai/databalanceanalysis/balance_measures.py
responsibleai/databalanceanalysis/constants.py
responsibleai/databalanceanalysis/data_balance_utils.py
responsibleai/databalanceanalysis/distribution_balance_measures.py
responsibleai/databalanceanalysis/feature_balance_measures.py
responsibleai/managers/__init__.py
responsibleai-0.36.0.dist-info/LICENSE
responsibleai-0.36.0.dist-info/METADATA
responsibleai-0.36.0.dist-info/WHEEL
responsibleai-0.36.0.dist-info/top_level.txt
responsibleai-0.36.0.dist-info/RECORD
